curcheck_manager/__main__.py
curcheck_manager/app.py
curcheck_manager/config.py
curcheck_manager/context.py
curcheck_manager/enums.py
curcheck_manager/generator.py
curcheck_manager/templates/full/app/__init__.py
curcheck_manager/templates/full/app/cookiecutter.json
curcheck_manager/templates/full/app/{{ cookiecutter.app_name }}/__init__.py
curcheck_manager/templates/full/app/{{ cookiecutter.app_name }}/models.py
curcheck_manager/templates/full/app/{{ cookiecutter.app_name }}/views.py
curcheck_manager/templates/full/project/cookiecutter.json
curcheck_manager/templates/full/project/{{ cookiecutter.project_name }}/env.env
curcheck_manager/templates/full/project/{{ cookiecutter.project_name }}/main.py
curcheck_manager/templates/full/project/{{ cookiecutter.project_name }}/pyproject.toml
curcheck_manager/templates/full/project/{{ cookiecutter.project_name }}/readme.md
curcheck_manager/templates/full/project/{{ cookiecutter.project_name }}/requirements.txt
curcheck_manager/templates/full/project/{{ cookiecutter.project_name }}/src/__init__.py
curcheck_manager/templates/full/project/{{ cookiecutter.project_name }}/src/app.py
curcheck_manager/templates/full/project/{{ cookiecutter.project_name }}/src/apps/__init__.py
curcheck_manager/templates/full/project/{{ cookiecutter.project_name }}/src/apps/main/__init__.py
curcheck_manager/templates/full/project/{{ cookiecutter.project_name }}/src/apps/main/models.py
curcheck_manager/templates/full/project/{{ cookiecutter.project_name }}/src/apps/main/views.py
curcheck_manager/templates/full/project/{{ cookiecutter.project_name }}/src/core/__init__.py
curcheck_manager/templates/full/project/{{ cookiecutter.project_name }}/src/core/bot_app.py
curcheck_manager/templates/full/project/{{ cookiecutter.project_name }}/src/core/db.py
curcheck_manager/templates/full/project/{{ cookiecutter.project_name }}/src/core/models/base.py
curcheck_manager/templates/full/project/{{ cookiecutter.project_name }}/src/core/models/timestamp.py
curcheck_manager-1.0.3.dist-info/entry_points.txt
curcheck_manager-1.0.3.dist-info/LICENSE
curcheck_manager-1.0.3.dist-info/METADATA
curcheck_manager-1.0.3.dist-info/WHEEL
curcheck_manager-1.0.3.dist-info/RECORD
